Metadata-Version: 2.1
Name: jackhash
Version: 1.0.5
Summary: Japanese, ASCII, Chinese, Korean Hash encoding
Home-page: https://github.com/amogorkon/jackhash
Author: Anselm Kiefner
Author-email: jackhash@anselm.kiefner.de
License: MIT
Keywords: hash encoding unicode
Platform: UNKNOWN
Classifier: Intended Audience :: Developers
Classifier: Natural Language :: English
Classifier: License :: OSI Approved :: MIT License
Classifier: Operating System :: OS Independent
Classifier: Programming Language :: Python :: 3 :: Only
Requires-Python: >=3.6
